bastion_api/__init__.py
bastion_api/bastion.py
bastion_api/dto/__init__.py
bastion_api/dto/device_dto.py
bastion_api/dto/old_dto.py
bastion_api/dto/organization_dto.py
bastion_api/dto/pass_dto.py
bastion_api/dto/person_dto.py
bastion_api/dto/points_dto.py
bastion_api/dto/support.py
bastion_api/error_handler.py
bastion_api/handlers.py
bastion_api-0.3.0.dist-info/LICENSE
bastion_api-0.3.0.dist-info/METADATA
bastion_api-0.3.0.dist-info/WHEEL
bastion_api-0.3.0.dist-info/RECORD
