Metadata-Version: 2.1
Name: bastion-api
Version: 0.3.0
Summary: Модуль интеграции с API Бастоин ИКС
Author: Mrkorogod
Requires-Python: >=3.10,<4.0
Classifier: Programming Language :: Python :: 3
Classifier: Programming Language :: Python :: 3.10
Classifier: Programming Language :: Python :: 3.11
